MANIFEST.in
README.md
setup.cfg
setup.py
docassemble/__init__.py
docassemble.hmctshelper.egg-info/PKG-INFO
docassemble.hmctshelper.egg-info/SOURCES.txt
docassemble.hmctshelper.egg-info/dependency_links.txt
docassemble.hmctshelper.egg-info/namespace_packages.txt
docassemble.hmctshelper.egg-info/not-zip-safe
docassemble.hmctshelper.egg-info/top_level.txt
docassemble/hmctshelper/__init__.py
docassemble/hmctshelper/data/questions/courts.yml
docassemble/hmctshelper/data/questions/n244.yml
docassemble/hmctshelper/data/questions/n244Questions.yml
docassemble/hmctshelper/data/questions/witnessStatement.yml
docassemble/hmctshelper/data/questions/witnessStatementQuestions.yml
docassemble/hmctshelper/data/sources/README.md
docassemble/hmctshelper/data/static/README.md
docassemble/hmctshelper/data/templates/README.md
docassemble/hmctshelper/data/templates/n244.pdf
docassemble/hmctshelper/data/templates/witnessStatement.docx