Metadata-Version: 2.1
Name: docassemble.hmctshelper
Version: 0.0.1
Summary: Interviews that help Litigants in Person complete HM Courts and Tribunals Service Forms
Home-page: https://docassemble.org
Author: Matt Pennington
Author-email: mp@tonic.works
License: The MIT License (MIT)
Platform: UNKNOWN
